LICENSE
MANIFEST.in
README.rst
setup.cfg
setup.py
fake_count/__init__.py
fake_count/app_settings.py
fake_count.egg-info/PKG-INFO
fake_count.egg-info/SOURCES.txt
fake_count.egg-info/dependency_links.txt
fake_count.egg-info/not-zip-safe
fake_count.egg-info/top_level.txt
fake_count/templates/_count.html
fake_count/templatetags/__init__.py
fake_count/templatetags/fake_count_tmpl.py