Metadata-Version: 1.0
Name: fake-count
Version: 0.0
Summary: Django app for displaying a random number based on the time of day.
Home-page: https://github.com/pro100git/django_fake_counter
Author: UNKNOWN
Author-email: bsana7931@gmail.com
License: BSD License
Platform: UNKNOWN
